new_library/__init__.py
rp_practice_library-0.1.0.dist-info/METADATA
rp_practice_library-0.1.0.dist-info/WHEEL
rp_practice_library-0.1.0.dist-info/RECORD
