Metadata-Version: 2.1
Name: rp-practice-library
Version: 0.1.0
Summary: A Learning Exercise
Home-page: https://github.com/robert-portelli3
License: MIT
Author: Robert Portelli
Author-email: github@robertportelli.com
Maintainer: Robert Portelli
Maintainer-email: github@robertportelli.com
Requires-Python: >=3.11,<4.0
Classifier: License :: OSI Approved :: MIT License
Classifier: Programming Language :: Python :: 3
Classifier: Programming Language :: Python :: 3.11
